parrot/USBSwitchController.py
parrot/__init__.py
robotframework_parrot_usbswitchcontroller-1.0.2.dist-info/LICENSE
robotframework_parrot_usbswitchcontroller-1.0.2.dist-info/METADATA
robotframework_parrot_usbswitchcontroller-1.0.2.dist-info/WHEEL
robotframework_parrot_usbswitchcontroller-1.0.2.dist-info/top_level.txt
robotframework_parrot_usbswitchcontroller-1.0.2.dist-info/RECORD
