Metadata-Version: 2.1
Name: robotframework-parrot-usbswitchcontroller
Version: 1.0.2
Summary: USB Switch Controller
Home-page: https://github.com/zilogic-systems/parrot
Author: Zilogic Systems
Author-email: code@zilogic.com
Classifier: Programming Language :: Python :: 3
Requires-Python: >=3.6
License-File: LICENSE
Requires-Dist: pyserial
Requires-Dist: robotframework
